{"1": ["reproduction", "reproductions"], "2": ["flag", "flags"], "3": ["universe", "universes"], "4": ["furniture", "furniture"], "5": ["poodle", "poodles"], "6": ["image", "images"], "7": ["mountain", "mountains"], "8": ["pig", "pigs"], "9": ["court", "courts"], "10": ["war", "wars"], "11": ["landscape", "landscapes"], "12": ["village", "villages"], "13": ["schnauzer", "schnauzers"], "14": ["car", "cars"], "15": ["score", "scores"], "16": ["stage", "stages"], "17": ["rose", "roses"], "18": ["edition", "editions"], "19": ["railway", "railways"], "20": ["forest", "forests"], "21": ["temple", "temples"], "22": ["lake", "lakes"], "23": ["train", "trains"], "24": ["vessel", "vessels"], "25": ["society", "societies"], "26": ["representation", "representations"], "27": ["set", "sets"], "28": ["city", "cities"], "29": ["size", "sizes"], "30": ["picture", "pictures"], "31": ["copy", "copies"], "32": ["house", "houses"], "33": ["swine", "swine"], "34": ["garden", "gardens"], "35": ["tree", "trees"], "36": ["figure", "figures"], "37": ["model", "models"], "38": ["potential", "potentials"], "39": ["replica", "replicas"], "40": ["form", "forms"], "41": ["course", "courses"], "42": ["scale", "scales"], "43": ["camera", "cameras"], "44": ["adult", "adults"], "45": ["world", "worlds"], "46": ["portrait", "portraits"], "47": ["golf", "golves"], "48": ["painter", "painters"], "49": ["version", "versions"], "50": ["painting", "paintings"]}