{"1": ["energy", "energies"], "2": ["importance", "importances"], "3": ["act", "acts"], "4": ["spectacle", "spectacles"], "5": ["enterprise", "enterprises"], "6": ["wall", "walls"], "7": ["scheme", "schemes"], "8": ["failure", "failures"], "9": ["plan", "plans"], "10": ["victory", "victories"], "11": ["view", "views"], "12": ["ruin", "ruins"], "13": ["folly", "follies"], "14": ["edifice", "edifices"], "15": ["difficulty", "difficulties"], "16": ["feat", "feats"], "17": ["rock", "rocks"], "18": ["piece", "pieces"], "19": ["scene", "scenes"], "20": ["pile", "piles"], "21": ["result", "results"], "22": ["growth", "growths"], "23": ["force", "forces"], "24": ["cliff", "cliffs"], "25": ["change", "changes"], "26": ["dimension", "dimensions"], "27": ["problem", "problems"], "28": ["sum", "sums"], "29": ["structure", "structures"], "30": ["success", "successes"], "31": ["amount", "amounts"], "32": ["proportion", "proportions"], "33": ["monument", "monuments"], "34": ["mass", "masses"], "35": ["size", "sizes"], "36": ["magnitude", "magnitudes"], "37": ["fabric", "fabrics"], "38": ["achievement", "achievements"], "39": ["height", "heights"], "40": ["event", "events"], "41": ["fact", "facts"], "42": ["power", "powers"], "43": ["effort", "efforts"], "44": ["mountain", "mountains"], "45": ["miracle", "miracles"], "46": ["scale", "scales"], "47": ["undertaking", "undertakings"], "48": ["whole", "wholes"], "49": ["work", "works"], "50": ["task", "tasks"]}