{"1": ["apricot", "apricots"], "2": ["cane", "canes"], "3": ["mind", "minds"], "4": ["walnut", "walnuts"], "5": ["food", "foods"], "6": ["cataract", "cataracts"], "7": ["head", "heads"], "8": ["maize", "maizes"], "9": ["cherry", "cherries"], "10": ["coconut", "coconuts"], "11": ["plantain", "plantains"], "12": ["youth", "youths"], "13": ["crop", "crops"], "14": ["stage", "stages"], "15": ["wheat", "wheats"], "16": ["melon", "melons"], "17": ["bean", "beans"], "18": ["ear", "ears"], "19": ["persimmon", "persimmons"], "20": ["egg", "eggs"], "21": ["potato", "potatoes"], "22": ["honey", "honeys"], "23": ["papaya", "papayas"], "24": ["peach", "peaches"], "25": ["orange", "oranges"], "26": ["date", "dates"], "27": ["plum", "plums"], "28": ["olive", "olives"], "29": ["childhood", "childhoods"], "30": ["nut", "nuts"], "31": ["gooseberry", "gooseberries"], "32": ["tomato", "tomatoes"], "33": ["pear", "pears"], "34": ["condition", "conditions"], "35": ["grain", "grains"], "36": ["age", "ages"], "37": ["mango", "mangoes"], "38": ["cervix", "cervixes"], "39": ["corn", "corns"], "40": ["one", "ones"], "41": ["fig", "figs"], "42": ["banana", "bananas"], "43": ["pod", "pods"], "44": ["state", "states"], "45": ["capsule", "capsules"], "46": ["seed", "seeds"], "47": ["apple", "apples"], "48": ["berry", "berries"], "49": ["grape", "grapes"], "50": ["fruit", "fruit"]}