{"1": ["expert", "experts"], "2": ["role", "roles"], "3": ["account", "accounts"], "4": ["composer", "composers"], "5": ["story", "stories"], "6": ["version", "versions"], "7": ["historian", "historians"], "8": ["speech", "speeches"], "9": ["debut", "debuts"], "10": ["singer", "singers"], "11": ["playwright", "playwrights"], "12": ["master", "masters"], "13": ["translation", "translations"], "14": ["painter", "painters"], "15": ["autobiography", "autobiographies"], "16": ["speaker", "speakers"], "17": ["movie", "movies"], "18": ["king", "kings"], "19": ["child", "children"], "20": ["drama", "dramata"], "21": ["actress", "actresses"], "22": ["guide", "guides"], "23": ["volume", "volumes"], "24": ["scholar", "scholars"], "25": ["actor", "actors"], "26": ["play", "plays"], "27": ["hero", "heroes"], "28": ["collection", "collections"], "29": ["history", "histories"], "30": ["album", "albums"], "31": ["documentary", "documentaries"], "32": ["director", "directors"], "33": ["restaurant", "restaurants"], "34": ["success", "successes"], "35": ["biography", "biographies"], "36": ["program", "programs"], "37": ["performance", "performances"], "38": ["artist", "artists"], "39": ["leader", "leaders"], "40": ["novelist", "novelists"], "41": ["production", "productions"], "42": ["study", "studies"], "43": ["poet", "poets"], "44": ["writer", "writers"], "45": ["film", "films"], "46": ["author", "authors"], "47": ["work", "works"], "48": ["book", "books"], "49": ["novel", "novels"], "50": ["series", "series"]}