{"1": ["approach", "approaches"], "2": ["distribution", "distributions"], "3": ["length", "lengths"], "4": ["method", "methods"], "5": ["balance", "balances"], "6": ["ratio", "ratios"], "7": ["algorithm", "algorithms"], "8": ["response", "responses"], "9": ["mix", "mixes"], "10": ["schedule", "schedules"], "11": ["decision", "decisions"], "12": ["plan", "plans"], "13": ["set", "sets"], "14": ["range", "ranges"], "15": ["therapy", "therapies"], "16": ["position", "positions"], "17": ["combination", "combinations"], "18": ["functioning", "functionings"], "19": ["concentration", "concentrations"], "20": ["temperature", "temperatures"], "21": ["theory", "theories"], "22": ["point", "points"], "23": ["structure", "structures"], "24": ["function", "functions"], "25": ["development", "developments"], "26": ["amount", "amounts"], "27": ["care", "cares"], "28": ["problem", "problems"], "29": ["management", "managements"], "30": ["treatment", "treatments"], "31": ["dose", "doses"], "32": ["growth", "growths"], "33": ["path", "paths"], "34": ["health", "healths"], "35": ["choice", "choices"], "36": ["rate", "rates"], "37": ["number", "numbers"], "38": ["result", "results"], "39": ["use", "uses"], "40": ["allocation", "allocations"], "41": ["performance", "performances"], "42": ["value", "values"], "43": ["size", "sizes"], "44": ["design", "designs"], "45": ["strategy", "strategies"], "46": ["control", "controls"], "47": ["policy", "policies"], "48": ["level", "levels"], "49": ["condition", "conditions"], "50": ["solution", "solutions"]}